LICENSE
MANIFEST.in
NOTICE
README.md
config.json
events_config.json
jumperble.template
jumperbleinitd.template
setup.cfg
setup.py
setup_service.sh
jumper_ble_logger/__init__.py
jumper_ble_logger/ble_logger.py
jumper_ble_logger/event_parser_middleware.py
jumper_ble_logger/gatt_protocol.py
jumper_ble_logger/hci_channel_user_socket.py
jumper_ble_logger.egg-info/PKG-INFO
jumper_ble_logger.egg-info/SOURCES.txt
jumper_ble_logger.egg-info/dependency_links.txt
jumper_ble_logger.egg-info/entry_points.txt
jumper_ble_logger.egg-info/requires.txt
jumper_ble_logger.egg-info/top_level.txt
jumper_ble_logger/hci_protocol/__init__.py
jumper_ble_logger/hci_protocol/hci_functions.py
jumper_ble_logger/hci_protocol/hci_protocol.py
jumper_ble_logger/hci_protocol/hci_sniffer.py
tests/__init__.py
tests/tests.py