Metadata-Version: 1.1
Name: jumper-ble-logger
Version: 0.1.3
Summary: Jumper GATT proxy for logging BLE traffic
Home-page: https://github.com/Jumperr-labs/jumper-ble-logger
Author: Jumper Team
Author-email: info@jumper.io
License: Apache 2.0
Download-URL: https://github.com/Jumperr-labs/jumper-ble-logger/archive/0.1.3.tar.gz
Keywords: ble,bluetooth,nrf52,gatt,logging,jumper
Platform: UNKNOWN
Classifier: Development Status :: 3 - Alpha
Classifier: Intended Audience :: Developers
Classifier: Topic :: Software Development :: Build Tools
Classifier: Programming Language :: Python :: 2
Classifier: Programming Language :: Python :: 2.7
Classifier: Programming Language :: Python :: 3
Classifier: Programming Language :: Python :: 3.3
Classifier: Programming Language :: Python :: 3.4
Classifier: Programming Language :: Python :: 3.5
